flaura/__init__.py
flaura/group.py
flaura/home.py
flaura/merge.py
flaura/pull.py
flaura/upstream.py
flaura-0.2.1.dist-info/entry_points.txt
flaura-0.2.1.dist-info/LICENSES/Apache-2.0.txt
flaura-0.2.1.dist-info/LICENSES/MIT.txt
flaura-0.2.1.dist-info/WHEEL
flaura-0.2.1.dist-info/METADATA
flaura-0.2.1.dist-info/RECORD
