Metadata-Version: 2.1
Name: flaura
Version: 0.2.1
Summary: Merge upstream with ease!
Home-page: https://github.com/waylovely-project/flaura.git
License: APACHE-2.0 OR MIT
Author: Fiana Fortressia
Author-email: fortressnordlys@outlook.com
Requires-Python: >=3.10,<4.0
Classifier: Development Status :: 3 - Alpha
Classifier: License :: Other/Proprietary License
Classifier: Programming Language :: Python :: 3
Classifier: Programming Language :: Python :: 3.10
Classifier: Topic :: Software Development :: Version Control
Requires-Dist: click (>=8.1.3,<9.0.0)
Requires-Dist: tomlkit (>=0.11.5,<0.12.0)
Project-URL: Repository, https://github.com/waylovely-project/flaura.git
